README.rst
setup.py
boardgamestats/__init__.py
boardgamestats/bgs.py
boardgamestats.egg-info/PKG-INFO
boardgamestats.egg-info/SOURCES.txt
boardgamestats.egg-info/dependency_links.txt
boardgamestats.egg-info/requires.txt
boardgamestats.egg-info/top_level.txt