Metadata-Version: 1.2
Name: boardgamestats
Version: 1.0.1
Summary: Python wrapper to pull latest board game rankings from wwww.boardgamegeek.com
Home-page: https://github.com/DnrkasEFF/BoardGameStats
Author: Aadhi Manivannan
Author-email: dnrkaseff360@gmail.com
License: MIT
Download-URL: https://github.com/DnrkasEFF/boardgamestats/archive/1.0.1.tar.gz
Keywords: board games,boardgamegeek,python,wrapper,board game stats
Platform: UNKNOWN
Requires-Python: >=3
